fiverr_api.py
fiverr_api-0.0.8.dist-info/LICENCE.txt
fiverr_api-0.0.8.dist-info/METADATA
fiverr_api-0.0.8.dist-info/WHEEL
fiverr_api-0.0.8.dist-info/top_level.txt
fiverr_api-0.0.8.dist-info/RECORD
